pymsio/readers/__init__.py
pymsio/readers/base.py
pymsio/readers/factory.py
pymsio/readers/mzml.py
pymsio/readers/thermo.py
pymsio/utils/util.py
pymsio-0.1.7.dist-info/licenses/LICENSE.txt
pymsio-0.1.7.dist-info/METADATA
pymsio-0.1.7.dist-info/WHEEL
pymsio-0.1.7.dist-info/top_level.txt
pymsio-0.1.7.dist-info/RECORD
