Metadata-Version: 2.4
Name: pymsio
Version: 0.1.7
Summary: MS I/O readers with optional vendor bindings
Author-email: Youngmin Park <youngmin.park@bertis.com>
License: Apache-2.0
Project-URL: Repository, https://github.com/bertis-informatics/pymsio
Project-URL: Issues, https://github.com/bertis-informatics/pymsio/issues
Requires-Python: >=3.8
License-File: LICENSE.txt
Requires-Dist: pythonnet>=3.0.5
Requires-Dist: numba>=0.47
Requires-Dist: numpy
Requires-Dist: pandas
Requires-Dist: tqdm
Requires-Dist: polars
Requires-Dist: lxml
Requires-Dist: isal
Requires-Dist: h5py
Dynamic: license-file
